pyecm/__init__.py
pyecm/soem_ext.cpp
pyecm/soem/__init__.py
pyecm/soem/py.typed
pyecm/soem/soem_ext.cpython-310-x86_64-linux-gnu.so
pyecm/soem/soem_ext.pyi
pyecm-0.0.3.dist-info/WHEEL
pyecm-0.0.3.dist-info/RECORD
pyecm-0.0.3.dist-info/METADATA
pyecm-0.0.3.dist-info/licenses/LICENSE
