Metadata-Version: 2.1
Name: pyecm
Version: 0.0.3
Summary: An EtherCAT MainDevice in Python
Author-Email: Jeff Anderson <kj4tmp@gmail.com>
Classifier: Programming Language :: Python :: 3
Classifier: License :: OSI Approved :: MIT License
Classifier: Operating System :: OS Independent
Project-URL: Homepage, https://github.com/kj4tmp/pyecm
Project-URL: Issues, https://github.com/kj4tmp/pyecm/issues
Requires-Python: >=3.10
Requires-Dist: numpy
